taskscordepm/__init__.py
taskscordepm/task_score.py
taskscordepm-0.1.22.dist-info/METADATA
taskscordepm-0.1.22.dist-info/WHEEL
taskscordepm-0.1.22.dist-info/RECORD
