Metadata-Version: 2.1
Name: taskscordepm
Version: 0.1.22
Summary: 
Author: Paulo Mulotto
Author-email: paulo.mulotto@gmail.com
Requires-Python: >=3.11,<4.0
Classifier: Programming Language :: Python :: 3
Classifier: Programming Language :: Python :: 3.11
Classifier: Programming Language :: Python :: 3.12
Requires-Dist: numpy (>=1.26.2,<2.0.0)
